{
	"format_version": "1.8.0",
	"animations": {
		"animation.demon.walk": {
			"loop": true,
			"animation_length": 1.24,
			"bones": {
				"Demon": {
					"rotation": {
						"0.12": {
							"vector": [0, 0, 0]
						},
						"0.64": {
							"vector": [7.5, 0, 0]
						},
						"1.24": {
							"vector": [0, 0, 0]
						}
					},
					"position": {
						"0.12": {
							"vector": [0, 0, 0]
						},
						"0.64": {
							"vector": [0, 2, 0]
						},
						"1.24": {
							"vector": [0, 0, 0]
						}
					}
				},
				"leftArm": {
					"rotation": {
						"0.0": {
							"vector": [0, 0, 0]
						},
						"0.56": {
							"vector": [9.99067, -0.43399, 2.46207]
						},
						"1.24": {
							"vector": [0, 0, 0]
						}
					},
					"position": {
						"0.0": {
							"vector": [0, 0, 0]
						},
						"0.56": {
							"vector": [0, -0.5, 0]
						},
						"1.24": {
							"vector": [0, 0, 0]
						}
					}
				},
				"rightArm": {
					"rotation": {
						"0.0": {
							"vector": [0, 0, 0]
						},
						"0.56": {
							"vector": [-5, 0, 0]
						},
						"1.24": {
							"vector": [0, 0, 0]
						}
					},
					"position": {
						"0.0": {
							"vector": [0, 0, 0]
						},
						"1.24": {
							"vector": [0, 0, 0]
						}
					}
				},
				"Os": {
					"rotation": {
						"0.0": {
							"vector": [0, 0, 0]
						},
						"0.56": {
							"vector": [2.08, 0, 0]
						},
						"1.24": {
							"vector": [0, 0, 0]
						}
					},
					"position": {
						"0.0": {
							"vector": [0, 0, 0]
						},
						"0.56": {
							"vector": [0, -1, 0]
						},
						"1.24": {
							"vector": [0, 0, 0]
						}
					}
				},
				"rightwings": {
					"rotation": {
						"0.0": {
							"vector": [0, 0, 0]
						},
						"0.84": {
							"vector": [0, -42.5, 0]
						},
						"1.24": {
							"vector": [0, 0, 0]
						}
					},
					"position": {
						"0.0": {
							"vector": [0, 0, 0]
						},
						"0.84": {
							"vector": [0, 1, 0]
						},
						"1.24": {
							"vector": [0, 0, 0]
						}
					}
				},
				"leftwings": {
					"rotation": {
						"0.0": {
							"vector": [0, 0, 0]
						},
						"0.84": {
							"vector": [0, 42.5, 0]
						},
						"1.24": {
							"vector": [0, 0, 0]
						}
					},
					"position": {
						"0.0": {
							"vector": [0, 0, 0]
						},
						"0.84": {
							"vector": [0, 1, 0]
						},
						"1.24": {
							"vector": [0, 0, 0]
						}
					}
				},
				"bone": {
					"rotation": {
						"0.0": {
							"vector": [0, 0, 0]
						},
						"0.56": {
							"vector": [10, 0, 0]
						},
						"1.24": {
							"vector": [0, 0, 0]
						}
					},
					"position": {
						"0.0": {
							"vector": [0, 0, 0]
						},
						"0.56": {
							"vector": [0, 0, 1]
						},
						"1.24": {
							"vector": [0, 0, 0]
						}
					}
				},
				"osbras": {
					"rotation": {
						"vector": [0, 0, 0]
					},
					"position": {
						"0.0": {
							"vector": [0, 0, 0]
						},
						"0.52": {
							"vector": [0, -0.25, 0]
						},
						"1.24": {
							"vector": [0, 0, 0]
						}
					}
				}
			}
		},
		"animation.demon.idle": {
			"loop": true,
			"animation_length": 1.70833,
			"bones": {
				"Demon": {
					"position": {
						"0.1667": {
							"vector": [0, 0, 0]
						},
						"0.8333": {
							"vector": [0, 2, 0]
						},
						"1.7083": {
							"vector": [0, 0, 0]
						}
					}
				},
				"leftArm": {
					"rotation": {
						"0.0": {
							"vector": [0, 0, 0]
						},
						"0.8333": {
							"vector": [0, 0, 2.5]
						},
						"1.7083": {
							"vector": [0, 0, 0]
						}
					},
					"position": {
						"0.0": {
							"vector": [0, 0, 0]
						},
						"0.8333": {
							"vector": [0, -1, 0]
						},
						"1.7083": {
							"vector": [0, 0, 0]
						}
					}
				},
				"rightArm": {
					"rotation": {
						"0.0": {
							"vector": [0, 0, 0]
						},
						"0.8333": {
							"vector": [0, 0, -2.5]
						},
						"1.7083": {
							"vector": [0, 0, 0]
						}
					},
					"position": {
						"0.0": {
							"vector": [0, 0, 0]
						},
						"0.8333": {
							"vector": [0, -1, 0]
						},
						"1.7083": {
							"vector": [0, 0, 0]
						}
					}
				},
				"Os": {
					"rotation": {
						"0.0": {
							"vector": [0, 0, 0]
						},
						"0.4167": {
							"vector": [-2.5, -7.5, 0]
						},
						"1.0833": {
							"vector": [0, 0, 0]
						}
					},
					"position": {
						"0.0": {
							"vector": [0, 0, 0]
						},
						"0.4167": {
							"vector": [0, -0.5, 0]
						},
						"1.0": {
							"vector": [0, 0, 0]
						}
					}
				},
				"rightwings": {
					"rotation": {
						"0.0": {
							"vector": [0, -2.5, 0]
						},
						"1.1667": {
							"vector": [0, -42.5, 0]
						},
						"1.7083": {
							"vector": [0, -2.5, 0]
						}
					},
					"position": {
						"0.0": {
							"vector": [0, 0, 0]
						},
						"1.0": {
							"vector": [0, 1, 0]
						},
						"1.7083": {
							"vector": [0, 0, 0]
						}
					}
				},
				"leftwings": {
					"rotation": {
						"0.0": {
							"vector": [0, -2.5, 0]
						},
						"1.1667": {
							"vector": [0, 40, 0]
						},
						"1.7083": {
							"vector": [0, -2.5, 0]
						}
					},
					"position": {
						"0.0": {
							"vector": [0, 0, 0]
						},
						"1.0": {
							"vector": [0, 1, 0]
						},
						"1.7083": {
							"vector": [0, 0, 0]
						}
					}
				},
				"bone": {
					"rotation": {
						"0.0": {
							"vector": [0, 0, 0]
						},
						"0.9583": {
							"vector": [7.5, 0, 0]
						},
						"1.7083": {
							"vector": [0, 0, 0]
						}
					}
				}
			},
			"particle_effects": {}
		}
	},
	"geckolib_format_version": 2
}